license.txt
patched_cli/__init__.py
patched_cli/__main__.py
patched_cli/app.py
patched_cli/client/__init__.py
patched_cli/client/patched.py
patched_cli/client/scm.py
patched_cli/client/sonar.py
patched_cli/envvars.py
patched_cli/git_helpers/__init__.py
patched_cli/git_helpers/git_helpers.py
patched_cli/models/__init__.py
patched_cli/models/common.py
patched_cli/models/enums.py
patched_cli/models/records.py
patched_cli/resources/languages_darwin_arm64.so
patched_cli/resources/languages_darwin_x86_64.so
patched_cli/resources/languages_linux_x86_64.so
patched_cli/resources/languages_windows_amd64.dll
patched_cli/scan/__init__.py
patched_cli/scan/common.py
patched_cli/scan/cwe.py
patched_cli/scan/filter.py
patched_cli/scan/flow.py
patched_cli/scan/formats.py
patched_cli/scan/severity.py
patched_cli/scan/vuln_provider.py
patched_cli/utils/__init__.py
patched_cli/utils/click_param_types.py
patched_cli/utils/ignore.py
patched_cli/utils/logging.py
patched_cli/utils/managed_files.py
patched_cli/utils/noop.py
patched_cli/utils/obfuscation.py
patched_cli/utils/parsers.py
patched_cli-1.1.4.dist-info/METADATA
patched_cli-1.1.4.dist-info/WHEEL
patched_cli-1.1.4.dist-info/entry_points.txt
patched_cli-1.1.4.dist-info/RECORD
