Metadata-Version: 2.1
Name: patched-cli
Version: 1.1.4
Summary: patched cli
License: Proprietary
Author: patched.codes
Requires-Python: >=3.10,<4.0
Classifier: License :: Other/Proprietary License
Classifier: Programming Language :: Python :: 3
Classifier: Programming Language :: Python :: 3.10
Classifier: Programming Language :: Python :: 3.11
Classifier: Programming Language :: Python :: 3.12
Requires-Dist: ast_comments (>=1.2.0,<1.3.0)
Requires-Dist: click (>=8.1.0,<8.2.0)
Requires-Dist: click-option-group (>=0.5.6,<0.6.0)
Requires-Dist: gitpython (>=3.1.40,<3.2.0)
Requires-Dist: pydantic (>=2.5.2,<2.6.0)
Requires-Dist: pygithub (>=2.1.1,<2.2.0)
Requires-Dist: python-gitlab (>=4.2.0,<5.0.0)
Requires-Dist: regex (==2023.10.3)
Requires-Dist: requests (>=2.31.0,<2.32.0)
Requires-Dist: semgrep (>=1.51.0,<2.0.0)
Requires-Dist: sentry-sdk (>=1.38.0,<1.39.0)
Requires-Dist: tree-sitter (>=0.20.4,<0.21.0)
